multithreaded_port_scanner.py
multithreaded_port_scanner-0.1.0.dist-info/METADATA
multithreaded_port_scanner-0.1.0.dist-info/WHEEL
multithreaded_port_scanner-0.1.0.dist-info/entry_points.txt
multithreaded_port_scanner-0.1.0.dist-info/licenses/LICENSE
multithreaded_port_scanner-0.1.0.dist-info/RECORD
