Metadata-Version: 2.4
Name: multithreaded-port-scanner
Version: 0.1.0
Summary: A simple, multi-threaded port scanner.
Project-URL: Homepage, https://github.com/Mohd-Yasir/Multithreaded-Port-Scanner
Author-email: Mohd Yasir <mohdxyasir@gmail.com>
License: MIT License
License-File: LICENSE
Keywords: network,port scanner,security
Classifier: License :: OSI Approved :: MIT License
Classifier: Operating System :: OS Independent
Classifier: Programming Language :: Python :: 3
Requires-Python: >=3.8
